{"dashboard": {"total": 18595, "versions": {"1.11.1": {"instances": 21}, "1.11.3": {"instances": 1}, "1.11.4": {"instances": 21}, "1.12.1": {"instances": 1}, "1.12.2": {"instances": 6}, "1.13.0": {"instances": 57}, "1.14.0": {"instances": 42}, "1.15.0": {"instances": 10}, "1.15.1": {"instances": 7}, "1.15.2": {"instances": 25}, "1.16.2": {"instances": 2}, "1.16.3": {"instances": 123}, "1.17.0": {"instances": 223}, "1.18.0": {"instances": 10}, "1.18.1": {"instances": 155}, "1.18.2": {"instances": 473}, "1.18.3": {"instances": 2469}, "1.19.0": {"instances": 85}, "1.19.1": {"instances": 4}, "1.19.2": {"instances": 26}, "1.19.3": {"instances": 219}, "1.19.4": {"instances": 27}, "1.19.5": {"instances": 12091}, "1.19.6": {"instances": 9190}, "1.19.7": {"instances": 3618}, "1.19.8": {"instances": 7741}, "1.5.1": {"instances": 2}}, "history": [{"date": "2022-01-07", "total": 17149, "versions": {"1.11.1": {"instances": 24}, "1.11.3": {"instances": 1}, "1.11.4": {"instances": 25}, "1.12.1": {"instances": 1}, "1.12.2": {"instances": 12}, "1.13.0": {"instances": 61}, "1.14.0": {"instances": 46}, "1.15.0": {"instances": 10}, "1.15.1": {"instances": 7}, "1.15.2": {"instances": 30}, "1.16.2": {"instances": 3}, "1.16.3": {"instances": 148}, "1.17.0": {"instances": 244}, "1.18.0": {"instances": 9}, "1.18.1": {"instances": 200}, "1.18.2": {"instances": 622}, "1.18.3": {"instances": 3601}, "1.19.0": {"instances": 171}, "1.19.0a0": {"instances": 1}, "1.19.1": {"instances": 11}, "1.19.2": {"instances": 67}, "1.19.3": {"instances": 426}, "1.19.4": {"instances": 57}, "1.19.5": {"instances": 13287}, "1.5.1": {"instances": 2}}}, {"date": "2022-01-08", "total": 17209, "versions": {"1.11.1": {"instances": 24}, "1.11.3": {"instances": 1}, "1.11.4": {"instances": 25}, "1.12.1": {"instances": 1}, "1.12.2": {"instances": 12}, "1.13.0": {"instances": 63}, "1.14.0": {"instances": 46}, "1.15.0": {"instances": 10}, "1.15.1": {"instances": 7}, "1.15.2": {"instances": 30}, "1.16.2": {"instances": 3}, "1.16.3": {"instances": 149}, "1.17.0": {"instances": 242}, "1.18.0": {"instances": 9}, "1.18.1": {"instances": 200}, "1.18.2": {"instances": 619}, "1.18.3": {"instances": 3535}, "1.19.0": {"instances": 167}, "1.19.0a0": {"instances": 1}, "1.19.1": {"instances": 11}, "1.19.2": {"instances": 65}, "1.19.3": {"instances": 416}, "1.19.4": {"instances": 57}, "1.19.5": {"instances": 13368}, "1.5.1": {"instances": 2}}}, {"date": "2022-01-09", "total": 17317, "versions": {"1.11.1": {"instances": 24}, "1.11.3": {"instances": 1}, "1.11.4": {"instances": 25}, "1.12.1": {"instances": 1}, "1.12.2": {"instances": 12}, "1.13.0": {"instances": 63}, "1.14.0": {"instances": 47}, "1.15.0": {"instances": 10}, "1.15.1": {"instances": 7}, "1.15.2": {"instances": 30}, "1.16.2": {"instances": 3}, "1.16.3": {"instances": 150}, "1.17.0": {"instances": 247}, "1.18.0": {"instances": 10}, "1.18.1": {"instances": 200}, "1.18.2": {"instances": 616}, "1.18.3": {"instances": 3487}, "1.19.0": {"instances": 164}, "1.19.0a0": {"instances": 1}, "1.19.1": {"instances": 11}, "1.19.2": {"instances": 63}, "1.19.3": {"instances": 410}, "1.19.4": {"instances": 56}, "1.19.5": {"instances": 13504}, "1.5.1": {"instances": 2}}}, {"date": "2022-01-10", "total": 17359, "versions": {"1.11.1": {"instances": 23}, "1.11.3": {"instances": 1}, "1.11.4": {"instances": 23}, "1.12.1": {"instances": 1}, "1.12.2": {"instances": 12}, "1.13.0": {"instances": 63}, "1.14.0": {"instances": 47}, "1.15.0": {"instances": 10}, "1.15.1": {"instances": 7}, "1.15.2": {"instances": 30}, "1.16.2": {"instances": 3}, "1.16.3": {"instances": 148}, "1.17.0": {"instances": 244}, "1.18.0": {"instances": 9}, "1.18.1": {"instances": 198}, "1.18.2": {"instances": 608}, "1.18.3": {"instances": 3440}, "1.19.0": {"instances": 161}, "1.19.0a0": {"instances": 1}, "1.19.1": {"instances": 9}, "1.19.2": {"instances": 59}, "1.19.3": {"instances": 404}, "1.19.4": {"instances": 56}, "1.19.5": {"instances": 13732}, "1.5.1": {"instances": 2}}}, {"date": "2022-01-11", "total": 17377, "versions": {"1.11.1": {"instances": 23}, "1.11.3": {"instances": 1}, "1.11.4": {"instances": 23}, "1.12.1": {"instances": 1}, "1.12.2": {"instances": 12}, "1.13.0": {"instances": 62}, "1.14.0": {"instances": 48}, "1.15.0": {"instances": 10}, "1.15.1": {"instances": 7}, "1.15.2": {"instances": 30}, "1.16.2": {"instances": 3}, "1.16.3": {"instances": 145}, "1.17.0": {"instances": 244}, "1.18.0": {"instances": 8}, "1.18.1": {"instances": 196}, "1.18.2": {"instances": 598}, "1.18.3": {"instances": 3369}, "1.19.0": {"instances": 157}, "1.19.0a0": {"instances": 1}, "1.19.1": {"instances": 9}, "1.19.2": {"instances": 56}, "1.19.3": {"instances": 389}, "1.19.4": {"instances": 53}, "1.19.5": {"instances": 13809}, "1.5.1": {"instances": 2}}}, {"date": "2022-01-12", "total": 17378, "versions": {"1.11.1": {"instances": 22}, "1.11.3": {"instances": 1}, "1.11.4": {"instances": 23}, "1.12.1": {"instances": 1}, "1.12.2": {"instances": 12}, "1.13.0": {"instances": 60}, "1.14.0": {"instances": 47}, "1.15.0": {"instances": 10}, "1.15.1": {"instances": 7}, "1.15.2": {"instances": 30}, "1.16.2": {"instances": 3}, "1.16.3": {"instances": 142}, "1.17.0": {"instances": 241}, "1.18.0": {"instances": 8}, "1.18.1": {"instances": 195}, "1.18.2": {"instances": 596}, "1.18.3": {"instances": 3299}, "1.19.0": {"instances": 155}, "1.19.0a0": {"instances": 1}, "1.19.1": {"instances": 9}, "1.19.2": {"instances": 53}, "1.19.3": {"instances": 384}, "1.19.4": {"instances": 52}, "1.19.5": {"instances": 13874}, "1.5.1": {"instances": 2}}}, {"date": "2022-01-13", "total": 17385, "versions": {"1.11.1": {"instances": 22}, "1.11.3": {"instances": 1}, "1.11.4": {"instances": 23}, "1.12.1": {"instances": 1}, "1.12.2": {"instances": 12}, "1.13.0": {"instances": 59}, "1.14.0": {"instances": 48}, "1.15.0": {"instances": 12}, "1.15.1": {"instances": 6}, "1.15.2": {"instances": 30}, "1.16.2": {"instances": 3}, "1.16.3": {"instances": 143}, "1.17.0": {"instances": 241}, "1.18.0": {"instances": 8}, "1.18.1": {"instances": 192}, "1.18.2": {"instances": 582}, "1.18.3": {"instances": 3260}, "1.19.0": {"instances": 152}, "1.19.0a0": {"instances": 1}, "1.19.1": {"instances": 9}, "1.19.2": {"instances": 53}, "1.19.3": {"instances": 369}, "1.19.4": {"instances": 50}, "1.19.5": {"instances": 13853}, "1.19.6": {"instances": 1254}, "1.5.1": {"instances": 2}}}, {"date": "2022-01-14", "total": 17557, "versions": {"1.11.1": {"instances": 22}, "1.11.3": {"instances": 1}, "1.11.4": {"instances": 23}, "1.12.1": {"instances": 1}, "1.12.2": {"instances": 10}, "1.13.0": {"instances": 59}, "1.14.0": {"instances": 46}, "1.15.0": {"instances": 12}, "1.15.1": {"instances": 6}, "1.15.2": {"instances": 30}, "1.16.2": {"instances": 3}, "1.16.3": {"instances": 141}, "1.17.0": {"instances": 239}, "1.18.0": {"instances": 9}, "1.18.1": {"instances": 190}, "1.18.2": {"instances": 575}, "1.18.3": {"instances": 3234}, "1.19.0": {"instances": 148}, "1.19.0a0": {"instances": 1}, "1.19.1": {"instances": 9}, "1.19.2": {"instances": 53}, "1.19.3": {"instances": 361}, "1.19.4": {"instances": 48}, "1.19.5": {"instances": 13794}, "1.19.6": {"instances": 2875}, "1.5.1": {"instances": 2}}}, {"date": "2022-01-15", "total": 17625, "versions": {"1.11.1": {"instances": 22}, "1.11.3": {"instances": 1}, "1.11.4": {"instances": 24}, "1.12.1": {"instances": 1}, "1.12.2": {"instances": 10}, "1.13.0": {"instances": 59}, "1.14.0": {"instances": 46}, "1.15.0": {"instances": 12}, "1.15.1": {"instances": 7}, "1.15.2": {"instances": 30}, "1.16.2": {"instances": 3}, "1.16.3": {"instances": 140}, "1.17.0": {"instances": 235}, "1.18.0": {"instances": 10}, "1.18.1": {"instances": 190}, "1.18.2": {"instances": 567}, "1.18.3": {"instances": 3195}, "1.19.0": {"instances": 144}, "1.19.1": {"instances": 9}, "1.19.2": {"instances": 52}, "1.19.3": {"instances": 350}, "1.19.4": {"instances": 46}, "1.19.5": {"instances": 13739}, "1.19.6": {"instances": 3898}, "1.5.1": {"instances": 2}}}, {"date": "2022-01-16", "total": 17752, "versions": {"1.11.1": {"instances": 23}, "1.11.3": {"instances": 1}, "1.11.4": {"instances": 24}, "1.12.1": {"instances": 1}, "1.12.2": {"instances": 10}, "1.13.0": {"instances": 58}, "1.14.0": {"instances": 47}, "1.15.0": {"instances": 12}, "1.15.1": {"instances": 7}, "1.15.2": {"instances": 29}, "1.16.2": {"instances": 3}, "1.16.3": {"instances": 139}, "1.17.0": {"instances": 231}, "1.18.0": {"instances": 10}, "1.18.1": {"instances": 189}, "1.18.2": {"instances": 562}, "1.18.3": {"instances": 3184}, "1.19.0": {"instances": 143}, "1.19.1": {"instances": 9}, "1.19.2": {"instances": 47}, "1.19.3": {"instances": 340}, "1.19.4": {"instances": 46}, "1.19.5": {"instances": 13701}, "1.19.6": {"instances": 4764}, "1.5.1": {"instances": 2}}}, {"date": "2022-01-17", "total": 17802, "versions": {"1.11.1": {"instances": 22}, "1.11.3": {"instances": 1}, "1.11.4": {"instances": 24}, "1.12.1": {"instances": 1}, "1.12.2": {"instances": 10}, "1.13.0": {"instances": 58}, "1.14.0": {"instances": 46}, "1.15.0": {"instances": 11}, "1.15.1": {"instances": 7}, "1.15.2": {"instances": 28}, "1.16.2": {"instances": 3}, "1.16.3": {"instances": 138}, "1.17.0": {"instances": 236}, "1.18.0": {"instances": 9}, "1.18.1": {"instances": 187}, "1.18.2": {"instances": 564}, "1.18.3": {"instances": 3141}, "1.19.0": {"instances": 139}, "1.19.1": {"instances": 9}, "1.19.2": {"instances": 44}, "1.19.3": {"instances": 339}, "1.19.4": {"instances": 45}, "1.19.5": {"instances": 13657}, "1.19.6": {"instances": 5487}, "1.5.1": {"instances": 2}}}, {"date": "2022-01-18", "total": 17797, "versions": {"1.11.1": {"instances": 21}, "1.11.3": {"instances": 1}, "1.11.4": {"instances": 24}, "1.12.1": {"instances": 1}, "1.12.2": {"instances": 10}, "1.13.0": {"instances": 58}, "1.14.0": {"instances": 46}, "1.15.0": {"instances": 11}, "1.15.1": {"instances": 8}, "1.15.2": {"instances": 28}, "1.16.2": {"instances": 3}, "1.16.3": {"instances": 135}, "1.17.0": {"instances": 238}, "1.18.0": {"instances": 9}, "1.18.1": {"instances": 185}, "1.18.2": {"instances": 561}, "1.18.3": {"instances": 3087}, "1.19.0": {"instances": 140}, "1.19.1": {"instances": 9}, "1.19.2": {"instances": 40}, "1.19.3": {"instances": 334}, "1.19.4": {"instances": 42}, "1.19.5": {"instances": 13441}, "1.19.6": {"instances": 6045}, "1.5.1": {"instances": 2}}}, {"date": "2022-01-19", "total": 17796, "versions": {"1.11.1": {"instances": 18}, "1.11.3": {"instances": 1}, "1.11.4": {"instances": 25}, "1.12.1": {"instances": 1}, "1.12.2": {"instances": 10}, "1.13.0": {"instances": 56}, "1.14.0": {"instances": 47}, "1.15.0": {"instances": 11}, "1.15.1": {"instances": 8}, "1.15.2": {"instances": 28}, "1.16.2": {"instances": 3}, "1.16.3": {"instances": 131}, "1.17.0": {"instances": 238}, "1.18.0": {"instances": 9}, "1.18.1": {"instances": 184}, "1.18.2": {"instances": 557}, "1.18.3": {"instances": 3029}, "1.19.0": {"instances": 133}, "1.19.1": {"instances": 9}, "1.19.2": {"instances": 39}, "1.19.3": {"instances": 327}, "1.19.4": {"instances": 42}, "1.19.5": {"instances": 13354}, "1.19.6": {"instances": 6519}, "1.5.1": {"instances": 2}}}, {"date": "2022-01-20", "total": 17834, "versions": {"1.11.1": {"instances": 18}, "1.11.3": {"instances": 1}, "1.11.4": {"instances": 25}, "1.12.1": {"instances": 1}, "1.12.2": {"instances": 10}, "1.13.0": {"instances": 55}, "1.14.0": {"instances": 47}, "1.15.0": {"instances": 11}, "1.15.1": {"instances": 8}, "1.15.2": {"instances": 28}, "1.16.2": {"instances": 3}, "1.16.3": {"instances": 129}, "1.17.0": {"instances": 239}, "1.18.0": {"instances": 8}, "1.18.1": {"instances": 184}, "1.18.2": {"instances": 553}, "1.18.3": {"instances": 2992}, "1.19.0": {"instances": 128}, "1.19.1": {"instances": 9}, "1.19.2": {"instances": 39}, "1.19.3": {"instances": 321}, "1.19.4": {"instances": 42}, "1.19.5": {"instances": 13283}, "1.19.6": {"instances": 6919}, "1.5.1": {"instances": 2}}}, {"date": "2022-01-21", "total": 17865, "versions": {"1.11.1": {"instances": 18}, "1.11.3": {"instances": 1}, "1.11.4": {"instances": 25}, "1.12.1": {"instances": 1}, "1.12.2": {"instances": 10}, "1.13.0": {"instances": 55}, "1.14.0": {"instances": 47}, "1.15.0": {"instances": 11}, "1.15.1": {"instances": 8}, "1.15.2": {"instances": 28}, "1.16.2": {"instances": 3}, "1.16.3": {"instances": 130}, "1.17.0": {"instances": 235}, "1.18.0": {"instances": 9}, "1.18.1": {"instances": 183}, "1.18.2": {"instances": 539}, "1.18.3": {"instances": 2961}, "1.19.0": {"instances": 127}, "1.19.1": {"instances": 9}, "1.19.2": {"instances": 39}, "1.19.3": {"instances": 317}, "1.19.4": {"instances": 42}, "1.19.5": {"instances": 13200}, "1.19.6": {"instances": 7379}, "1.5.1": {"instances": 2}}}, {"date": "2022-01-22", "total": 17905, "versions": {"1.11.1": {"instances": 19}, "1.11.3": {"instances": 1}, "1.11.4": {"instances": 25}, "1.12.1": {"instances": 1}, "1.12.2": {"instances": 9}, "1.13.0": {"instances": 54}, "1.14.0": {"instances": 47}, "1.15.0": {"instances": 11}, "1.15.1": {"instances": 8}, "1.15.2": {"instances": 28}, "1.16.2": {"instances": 3}, "1.16.3": {"instances": 134}, "1.17.0": {"instances": 233}, "1.18.0": {"instances": 9}, "1.18.1": {"instances": 181}, "1.18.2": {"instances": 539}, "1.18.3": {"instances": 2935}, "1.19.0": {"instances": 124}, "1.19.1": {"instances": 8}, "1.19.2": {"instances": 37}, "1.19.3": {"instances": 311}, "1.19.4": {"instances": 42}, "1.19.5": {"instances": 13143}, "1.19.6": {"instances": 7826}, "1.5.1": {"instances": 2}}}, {"date": "2022-01-23", "total": 18127, "versions": {"1.11.1": {"instances": 18}, "1.11.3": {"instances": 1}, "1.11.4": {"instances": 24}, "1.12.1": {"instances": 1}, "1.12.2": {"instances": 9}, "1.13.0": {"instances": 55}, "1.14.0": {"instances": 47}, "1.15.0": {"instances": 11}, "1.15.1": {"instances": 8}, "1.15.2": {"instances": 28}, "1.16.2": {"instances": 3}, "1.16.3": {"instances": 133}, "1.17.0": {"instances": 229}, "1.18.0": {"instances": 9}, "1.18.1": {"instances": 181}, "1.18.2": {"instances": 536}, "1.18.3": {"instances": 2897}, "1.19.0": {"instances": 119}, "1.19.1": {"instances": 8}, "1.19.2": {"instances": 37}, "1.19.3": {"instances": 309}, "1.19.4": {"instances": 41}, "1.19.5": {"instances": 12959}, "1.19.6": {"instances": 8355}, "1.5.1": {"instances": 2}}}, {"date": "2022-01-24", "total": 18219, "versions": {"1.11.1": {"instances": 18}, "1.11.3": {"instances": 1}, "1.11.4": {"instances": 24}, "1.12.1": {"instances": 1}, "1.12.2": {"instances": 9}, "1.13.0": {"instances": 57}, "1.14.0": {"instances": 47}, "1.15.0": {"instances": 11}, "1.15.1": {"instances": 8}, "1.15.2": {"instances": 26}, "1.16.2": {"instances": 3}, "1.16.3": {"instances": 134}, "1.17.0": {"instances": 229}, "1.18.0": {"instances": 9}, "1.18.1": {"instances": 184}, "1.18.2": {"instances": 528}, "1.18.3": {"instances": 2874}, "1.19.0": {"instances": 119}, "1.19.1": {"instances": 8}, "1.19.2": {"instances": 36}, "1.19.3": {"instances": 301}, "1.19.4": {"instances": 39}, "1.19.5": {"instances": 12930}, "1.19.6": {"instances": 8806}, "1.5.1": {"instances": 2}}}, {"date": "2022-01-25", "total": 18250, "versions": {"1.11.1": {"instances": 18}, "1.11.3": {"instances": 1}, "1.11.4": {"instances": 23}, "1.12.1": {"instances": 1}, "1.12.2": {"instances": 8}, "1.13.0": {"instances": 57}, "1.14.0": {"instances": 48}, "1.15.0": {"instances": 12}, "1.15.1": {"instances": 8}, "1.15.2": {"instances": 27}, "1.16.2": {"instances": 3}, "1.16.3": {"instances": 133}, "1.17.0": {"instances": 227}, "1.18.0": {"instances": 9}, "1.18.1": {"instances": 182}, "1.18.2": {"instances": 522}, "1.18.3": {"instances": 2840}, "1.19.0": {"instances": 113}, "1.19.1": {"instances": 8}, "1.19.2": {"instances": 36}, "1.19.3": {"instances": 294}, "1.19.4": {"instances": 39}, "1.19.5": {"instances": 12889}, "1.19.6": {"instances": 9087}, "1.5.1": {"instances": 2}}}, {"date": "2022-01-26", "total": 18254, "versions": {"1.11.1": {"instances": 18}, "1.11.3": {"instances": 1}, "1.11.4": {"instances": 23}, "1.12.1": {"instances": 1}, "1.12.2": {"instances": 8}, "1.13.0": {"instances": 58}, "1.14.0": {"instances": 47}, "1.15.0": {"instances": 12}, "1.15.1": {"instances": 8}, "1.15.2": {"instances": 25}, "1.16.2": {"instances": 3}, "1.16.3": {"instances": 133}, "1.17.0": {"instances": 226}, "1.18.0": {"instances": 9}, "1.18.1": {"instances": 182}, "1.18.2": {"instances": 514}, "1.18.3": {"instances": 2807}, "1.19.0": {"instances": 111}, "1.19.1": {"instances": 8}, "1.19.2": {"instances": 36}, "1.19.3": {"instances": 285}, "1.19.4": {"instances": 37}, "1.19.5": {"instances": 12814}, "1.19.6": {"instances": 9166}, "1.19.7": {"instances": 1436}, "1.5.1": {"instances": 2}}}, {"date": "2022-01-27", "total": 18309, "versions": {"1.11.1": {"instances": 18}, "1.11.3": {"instances": 1}, "1.11.4": {"instances": 24}, "1.12.1": {"instances": 1}, "1.12.2": {"instances": 8}, "1.13.0": {"instances": 57}, "1.14.0": {"instances": 45}, "1.15.0": {"instances": 12}, "1.15.1": {"instances": 8}, "1.15.2": {"instances": 25}, "1.16.2": {"instances": 3}, "1.16.3": {"instances": 134}, "1.17.0": {"instances": 225}, "1.18.0": {"instances": 10}, "1.18.1": {"instances": 182}, "1.18.2": {"instances": 508}, "1.18.3": {"instances": 2752}, "1.19.0": {"instances": 106}, "1.19.1": {"instances": 8}, "1.19.2": {"instances": 35}, "1.19.3": {"instances": 278}, "1.19.4": {"instances": 37}, "1.19.5": {"instances": 12776}, "1.19.6": {"instances": 9178}, "1.19.7": {"instances": 3019}, "1.5.1": {"instances": 2}}}, {"date": "2022-01-28", "total": 18316, "versions": {"1.11.1": {"instances": 18}, "1.11.3": {"instances": 1}, "1.11.4": {"instances": 24}, "1.12.1": {"instances": 1}, "1.12.2": {"instances": 8}, "1.13.0": {"instances": 56}, "1.14.0": {"instances": 45}, "1.15.0": {"instances": 12}, "1.15.1": {"instances": 8}, "1.15.2": {"instances": 26}, "1.16.2": {"instances": 1}, "1.16.3": {"instances": 136}, "1.17.0": {"instances": 225}, "1.18.0": {"instances": 9}, "1.18.1": {"instances": 173}, "1.18.2": {"instances": 504}, "1.18.3": {"instances": 2700}, "1.19.0": {"instances": 100}, "1.19.1": {"instances": 8}, "1.19.2": {"instances": 35}, "1.19.3": {"instances": 262}, "1.19.4": {"instances": 33}, "1.19.5": {"instances": 12672}, "1.19.6": {"instances": 9178}, "1.19.7": {"instances": 3583}, "1.19.8": {"instances": 1094}, "1.5.1": {"instances": 2}}}, {"date": "2022-01-29", "total": 18293, "versions": {"1.11.1": {"instances": 18}, "1.11.3": {"instances": 1}, "1.11.4": {"instances": 24}, "1.12.1": {"instances": 1}, "1.12.2": {"instances": 8}, "1.13.0": {"instances": 56}, "1.14.0": {"instances": 44}, "1.15.0": {"instances": 11}, "1.15.1": {"instances": 8}, "1.15.2": {"instances": 26}, "1.16.2": {"instances": 1}, "1.16.3": {"instances": 137}, "1.17.0": {"instances": 228}, "1.18.0": {"instances": 9}, "1.18.1": {"instances": 170}, "1.18.2": {"instances": 496}, "1.18.3": {"instances": 2662}, "1.19.0": {"instances": 99}, "1.19.1": {"instances": 7}, "1.19.2": {"instances": 34}, "1.19.3": {"instances": 258}, "1.19.4": {"instances": 33}, "1.19.5": {"instances": 12422}, "1.19.6": {"instances": 9180}, "1.19.7": {"instances": 3604}, "1.19.8": {"instances": 2819}, "1.5.1": {"instances": 2}}}, {"date": "2022-01-30", "total": 18326, "versions": {"1.11.1": {"instances": 18}, "1.11.3": {"instances": 1}, "1.11.4": {"instances": 24}, "1.12.1": {"instances": 1}, "1.12.2": {"instances": 8}, "1.13.0": {"instances": 55}, "1.14.0": {"instances": 44}, "1.15.0": {"instances": 11}, "1.15.1": {"instances": 8}, "1.15.2": {"instances": 26}, "1.16.2": {"instances": 1}, "1.16.3": {"instances": 132}, "1.17.0": {"instances": 226}, "1.18.0": {"instances": 9}, "1.18.1": {"instances": 169}, "1.18.2": {"instances": 497}, "1.18.3": {"instances": 2638}, "1.19.0": {"instances": 96}, "1.19.1": {"instances": 7}, "1.19.2": {"instances": 34}, "1.19.3": {"instances": 252}, "1.19.4": {"instances": 30}, "1.19.5": {"instances": 12407}, "1.19.6": {"instances": 9183}, "1.19.7": {"instances": 3606}, "1.19.8": {"instances": 4154}, "1.5.1": {"instances": 2}}}, {"date": "2022-01-31", "total": 18402, "versions": {"1.11.1": {"instances": 18}, "1.11.3": {"instances": 1}, "1.11.4": {"instances": 23}, "1.12.1": {"instances": 1}, "1.12.2": {"instances": 8}, "1.13.0": {"instances": 55}, "1.14.0": {"instances": 43}, "1.15.0": {"instances": 11}, "1.15.1": {"instances": 8}, "1.15.2": {"instances": 26}, "1.16.2": {"instances": 1}, "1.16.3": {"instances": 131}, "1.17.0": {"instances": 227}, "1.18.0": {"instances": 10}, "1.18.1": {"instances": 168}, "1.18.2": {"instances": 498}, "1.18.3": {"instances": 2601}, "1.19.0": {"instances": 94}, "1.19.1": {"instances": 6}, "1.19.2": {"instances": 34}, "1.19.3": {"instances": 248}, "1.19.4": {"instances": 30}, "1.19.5": {"instances": 12365}, "1.19.6": {"instances": 9187}, "1.19.7": {"instances": 3610}, "1.19.8": {"instances": 5069}, "1.5.1": {"instances": 2}}}, {"date": "2022-02-01", "total": 18550, "versions": {"1.11.1": {"instances": 17}, "1.11.3": {"instances": 1}, "1.11.4": {"instances": 22}, "1.12.1": {"instances": 1}, "1.12.2": {"instances": 7}, "1.13.0": {"instances": 55}, "1.14.0": {"instances": 43}, "1.15.0": {"instances": 11}, "1.15.1": {"instances": 8}, "1.15.2": {"instances": 26}, "1.16.2": {"instances": 1}, "1.16.3": {"instances": 128}, "1.17.0": {"instances": 227}, "1.18.0": {"instances": 10}, "1.18.1": {"instances": 164}, "1.18.2": {"instances": 498}, "1.18.3": {"instances": 2581}, "1.19.0": {"instances": 92}, "1.19.1": {"instances": 6}, "1.19.2": {"instances": 32}, "1.19.3": {"instances": 245}, "1.19.4": {"instances": 29}, "1.19.5": {"instances": 12305}, "1.19.6": {"instances": 9187}, "1.19.7": {"instances": 3613}, "1.19.8": {"instances": 5845}, "1.5.1": {"instances": 2}}}, {"date": "2022-02-02", "total": 18431, "versions": {"1.11.1": {"instances": 19}, "1.11.3": {"instances": 1}, "1.11.4": {"instances": 22}, "1.12.1": {"instances": 1}, "1.12.2": {"instances": 7}, "1.13.0": {"instances": 55}, "1.14.0": {"instances": 43}, "1.15.0": {"instances": 10}, "1.15.1": {"instances": 7}, "1.15.2": {"instances": 25}, "1.16.2": {"instances": 1}, "1.16.3": {"instances": 126}, "1.17.0": {"instances": 227}, "1.18.0": {"instances": 10}, "1.18.1": {"instances": 162}, "1.18.2": {"instances": 492}, "1.18.3": {"instances": 2544}, "1.19.0": {"instances": 90}, "1.19.1": {"instances": 6}, "1.19.2": {"instances": 30}, "1.19.3": {"instances": 241}, "1.19.4": {"instances": 28}, "1.19.5": {"instances": 12140}, "1.19.6": {"instances": 9189}, "1.19.7": {"instances": 3614}, "1.19.8": {"instances": 6425}, "1.5.1": {"instances": 2}}}, {"date": "2022-02-03", "total": 18578, "versions": {"1.11.1": {"instances": 19}, "1.11.3": {"instances": 1}, "1.11.4": {"instances": 21}, "1.12.1": {"instances": 1}, "1.12.2": {"instances": 7}, "1.13.0": {"instances": 56}, "1.14.0": {"instances": 43}, "1.15.0": {"instances": 10}, "1.15.1": {"instances": 7}, "1.15.2": {"instances": 25}, "1.16.2": {"instances": 1}, "1.16.3": {"instances": 126}, "1.17.0": {"instances": 224}, "1.18.0": {"instances": 10}, "1.18.1": {"instances": 160}, "1.18.2": {"instances": 485}, "1.18.3": {"instances": 2506}, "1.19.0": {"instances": 89}, "1.19.1": {"instances": 6}, "1.19.2": {"instances": 29}, "1.19.3": {"instances": 235}, "1.19.4": {"instances": 27}, "1.19.5": {"instances": 11905}, "1.19.6": {"instances": 9190}, "1.19.7": {"instances": 3615}, "1.19.8": {"instances": 6903}, "1.5.1": {"instances": 2}}}, {"date": "2022-02-04", "total": 18590, "versions": {"1.11.1": {"instances": 20}, "1.11.3": {"instances": 1}, "1.11.4": {"instances": 21}, "1.12.1": {"instances": 1}, "1.12.2": {"instances": 7}, "1.13.0": {"instances": 57}, "1.14.0": {"instances": 42}, "1.15.0": {"instances": 10}, "1.15.1": {"instances": 7}, "1.15.2": {"instances": 25}, "1.16.2": {"instances": 2}, "1.16.3": {"instances": 125}, "1.17.0": {"instances": 224}, "1.18.0": {"instances": 10}, "1.18.1": {"instances": 156}, "1.18.2": {"instances": 481}, "1.18.3": {"instances": 2487}, "1.19.0": {"instances": 86}, "1.19.1": {"instances": 6}, "1.19.2": {"instances": 28}, "1.19.3": {"instances": 231}, "1.19.4": {"instances": 27}, "1.19.5": {"instances": 12027}, "1.19.6": {"instances": 9190}, "1.19.7": {"instances": 3618}, "1.19.8": {"instances": 7332}, "1.5.1": {"instances": 2}}}, {"date": "2022-02-05", "total": 18595, "versions": {"1.11.1": {"instances": 21}, "1.11.3": {"instances": 1}, "1.11.4": {"instances": 21}, "1.12.1": {"instances": 1}, "1.12.2": {"instances": 6}, "1.13.0": {"instances": 57}, "1.14.0": {"instances": 42}, "1.15.0": {"instances": 10}, "1.15.1": {"instances": 7}, "1.15.2": {"instances": 25}, "1.16.2": {"instances": 2}, "1.16.3": {"instances": 123}, "1.17.0": {"instances": 223}, "1.18.0": {"instances": 10}, "1.18.1": {"instances": 155}, "1.18.2": {"instances": 473}, "1.18.3": {"instances": 2469}, "1.19.0": {"instances": 85}, "1.19.1": {"instances": 4}, "1.19.2": {"instances": 26}, "1.19.3": {"instances": 219}, "1.19.4": {"instances": 27}, "1.19.5": {"instances": 12091}, "1.19.6": {"instances": 9190}, "1.19.7": {"instances": 3618}, "1.19.8": {"instances": 7741}, "1.5.1": {"instances": 2}}}]}, "inlineconfirm": {"total": 503, "versions": {"1.0.0": {"instances": 1}, "1.0.1": {"instances": 3}, "1.1.0": {"instances": 26}, "1.1.2": {"instances": 25}, "1.1.4": {"instances": 473}}, "history": [{"date": "2022-01-07", "total": 506, "versions": {"1.0.0": {"instances": 1}, "1.0.1": {"instances": 5}, "1.1.0": {"instances": 28}, "1.1.2": {"instances": 29}, "1.1.4": {"instances": 463}}}, {"date": "2022-01-08", "total": 503, "versions": {"1.0.0": {"instances": 1}, "1.0.1": {"instances": 5}, "1.1.0": {"instances": 27}, "1.1.2": {"instances": 29}, "1.1.4": {"instances": 460}}}, {"date": "2022-01-09", "total": 506, "versions": {"1.0.0": {"instances": 1}, "1.0.1": {"instances": 5}, "1.1.0": {"instances": 27}, "1.1.2": {"instances": 30}, "1.1.4": {"instances": 463}}}, {"date": "2022-01-10", "total": 504, "versions": {"1.0.0": {"instances": 1}, "1.0.1": {"instances": 5}, "1.1.0": {"instances": 27}, "1.1.2": {"instances": 30}, "1.1.4": {"instances": 460}}}, {"date": "2022-01-11", "total": 505, "versions": {"1.0.0": {"instances": 1}, "1.0.1": {"instances": 5}, "1.1.0": {"instances": 28}, "1.1.2": {"instances": 28}, "1.1.4": {"instances": 465}}}, {"date": "2022-01-12", "total": 505, "versions": {"1.0.0": {"instances": 1}, "1.0.1": {"instances": 5}, "1.1.0": {"instances": 28}, "1.1.2": {"instances": 28}, "1.1.4": {"instances": 467}}}, {"date": "2022-01-13", "total": 503, "versions": {"1.0.0": {"instances": 1}, "1.0.1": {"instances": 5}, "1.1.0": {"instances": 28}, "1.1.2": {"instances": 28}, "1.1.4": {"instances": 465}}}, {"date": "2022-01-14", "total": 505, "versions": {"1.0.0": {"instances": 1}, "1.0.1": {"instances": 5}, "1.1.0": {"instances": 28}, "1.1.2": {"instances": 29}, "1.1.4": {"instances": 467}}}, {"date": "2022-01-15", "total": 504, "versions": {"1.0.0": {"instances": 1}, "1.0.1": {"instances": 5}, "1.1.0": {"instances": 29}, "1.1.2": {"instances": 28}, "1.1.4": {"instances": 467}}}, {"date": "2022-01-16", "total": 504, "versions": {"1.0.0": {"instances": 1}, "1.0.1": {"instances": 5}, "1.1.0": {"instances": 29}, "1.1.2": {"instances": 28}, "1.1.4": {"instances": 467}}}, {"date": "2022-01-17", "total": 504, "versions": {"1.0.0": {"instances": 1}, "1.0.1": {"instances": 5}, "1.1.0": {"instances": 30}, "1.1.2": {"instances": 28}, "1.1.4": {"instances": 468}}}, {"date": "2022-01-18", "total": 504, "versions": {"1.0.0": {"instances": 1}, "1.0.1": {"instances": 5}, "1.1.0": {"instances": 30}, "1.1.2": {"instances": 28}, "1.1.4": {"instances": 469}}}, {"date": "2022-01-19", "total": 505, "versions": {"1.0.0": {"instances": 1}, "1.0.1": {"instances": 5}, "1.1.0": {"instances": 30}, "1.1.2": {"instances": 27}, "1.1.4": {"instances": 470}}}, {"date": "2022-01-20", "total": 506, "versions": {"1.0.0": {"instances": 1}, "1.0.1": {"instances": 4}, "1.1.0": {"instances": 30}, "1.1.2": {"instances": 27}, "1.1.4": {"instances": 471}}}, {"date": "2022-01-21", "total": 506, "versions": {"1.0.0": {"instances": 1}, "1.0.1": {"instances": 4}, "1.1.0": {"instances": 30}, "1.1.2": {"instances": 27}, "1.1.4": {"instances": 472}}}, {"date": "2022-01-22", "total": 508, "versions": {"1.0.0": {"instances": 1}, "1.0.1": {"instances": 4}, "1.1.0": {"instances": 30}, "1.1.2": {"instances": 26}, "1.1.4": {"instances": 474}}}, {"date": "2022-01-23", "total": 509, "versions": {"1.0.0": {"instances": 1}, "1.0.1": {"instances": 4}, "1.1.0": {"instances": 30}, "1.1.2": {"instances": 26}, "1.1.4": {"instances": 476}}}, {"date": "2022-01-24", "total": 504, "versions": {"1.0.0": {"instances": 1}, "1.0.1": {"instances": 3}, "1.1.0": {"instances": 29}, "1.1.2": {"instances": 26}, "1.1.4": {"instances": 473}}}, {"date": "2022-01-25", "total": 503, "versions": {"1.0.0": {"instances": 1}, "1.0.1": {"instances": 3}, "1.1.0": {"instances": 29}, "1.1.2": {"instances": 27}, "1.1.4": {"instances": 471}}}, {"date": "2022-01-26", "total": 502, "versions": {"1.0.0": {"instances": 1}, "1.0.1": {"instances": 3}, "1.1.0": {"instances": 29}, "1.1.2": {"instances": 27}, "1.1.4": {"instances": 470}}}, {"date": "2022-01-27", "total": 497, "versions": {"1.0.0": {"instances": 1}, "1.0.1": {"instances": 3}, "1.1.0": {"instances": 29}, "1.1.2": {"instances": 27}, "1.1.4": {"instances": 466}}}, {"date": "2022-01-28", "total": 497, "versions": {"1.0.0": {"instances": 1}, "1.0.1": {"instances": 3}, "1.1.0": {"instances": 30}, "1.1.2": {"instances": 26}, "1.1.4": {"instances": 465}}}, {"date": "2022-01-29", "total": 498, "versions": {"1.0.0": {"instances": 1}, "1.0.1": {"instances": 3}, "1.1.0": {"instances": 30}, "1.1.2": {"instances": 27}, "1.1.4": {"instances": 465}}}, {"date": "2022-01-30", "total": 502, "versions": {"1.0.0": {"instances": 1}, "1.0.1": {"instances": 4}, "1.1.0": {"instances": 30}, "1.1.2": {"instances": 27}, "1.1.4": {"instances": 469}}}, {"date": "2022-01-31", "total": 502, "versions": {"1.0.0": {"instances": 1}, "1.0.1": {"instances": 4}, "1.1.0": {"instances": 30}, "1.1.2": {"instances": 28}, "1.1.4": {"instances": 468}}}, {"date": "2022-02-01", "total": 501, "versions": {"1.0.0": {"instances": 1}, "1.0.1": {"instances": 4}, "1.1.0": {"instances": 30}, "1.1.2": {"instances": 27}, "1.1.4": {"instances": 469}}}, {"date": "2022-02-02", "total": 504, "versions": {"1.0.0": {"instances": 1}, "1.0.1": {"instances": 3}, "1.1.0": {"instances": 28}, "1.1.2": {"instances": 25}, "1.1.4": {"instances": 474}}}, {"date": "2022-02-03", "total": 502, "versions": {"1.0.0": {"instances": 1}, "1.0.1": {"instances": 3}, "1.1.0": {"instances": 27}, "1.1.2": {"instances": 25}, "1.1.4": {"instances": 472}}}, {"date": "2022-02-04", "total": 504, "versions": {"1.0.0": {"instances": 1}, "1.0.1": {"instances": 3}, "1.1.0": {"instances": 27}, "1.1.2": {"instances": 25}, "1.1.4": {"instances": 474}}}, {"date": "2022-02-05", "total": 503, "versions": {"1.0.0": {"instances": 1}, "1.0.1": {"instances": 3}, "1.1.0": {"instances": 26}, "1.1.2": {"instances": 25}, "1.1.4": {"instances": 473}}}]}}